stan_language_server/__init__.py
stan_language_server/cli.py
stan_language_server/server.py
stan_language_server/stan-functions.txt
stan_language_server/stan-keywords.txt
stan_language_server/utils.py
stan_language_server-0.1.0.dist-info/LICENSE
stan_language_server-0.1.0.dist-info/METADATA
stan_language_server-0.1.0.dist-info/WHEEL
stan_language_server-0.1.0.dist-info/entry_points.txt
stan_language_server-0.1.0.dist-info/RECORD
