Metadata-Version: 2.1
Name: stan-language-server
Version: 0.1.0
Summary: Language server implementation for STAN, using pygls.
Author: Leon Zong
Author-email: leon@leonzong.com
Requires-Python: >=3.9,<4.0
Classifier: Programming Language :: Python :: 3
Classifier: Programming Language :: Python :: 3.9
Classifier: Programming Language :: Python :: 3.10
Classifier: Programming Language :: Python :: 3.11
Classifier: Programming Language :: Python :: 3.12
Requires-Dist: pygls (>=1.3.1,<2.0.0)
